README.rst
setup.py
src/sphinxcontrib/__init__.py
src/sphinxcontrib.divparams.egg-info/PKG-INFO
src/sphinxcontrib.divparams.egg-info/SOURCES.txt
src/sphinxcontrib.divparams.egg-info/dependency_links.txt
src/sphinxcontrib.divparams.egg-info/namespace_packages.txt
src/sphinxcontrib.divparams.egg-info/requires.txt
src/sphinxcontrib.divparams.egg-info/top_level.txt
src/sphinxcontrib/divparams/__init__.py
src/sphinxcontrib/divparams/implementation.py
src/sphinxcontrib/divparams/_static/divparams.css
src/sphinxcontrib/divparams/_templates/layout.html