Metadata-Version: 1.1
Name: sphinxcontrib.divparams
Version: 0.0.6
Summary: Converts parameter tables in HTML documentation generated by Sphinx into <div>'s.
Home-page: https://github.com/sphinxcontrib-divparams
Author: Pavel Kretov
Author-email: firegurafiku@gmail.com
License: MIT
Keywords: helpers
Platform: UNKNOWN
Classifier: Programming Language :: Python
Classifier: Programming Language :: Python :: 2.6
Classifier: Programming Language :: Python :: 2.7
Classifier: Programming Language :: Python :: 3.3
Classifier: Programming Language :: Python :: 3.4
Classifier: Programming Language :: Python :: 3.5
Classifier: Development Status :: 2 - Pre-Alpha
Classifier: Topic :: Documentation
Classifier: Intended Audience :: Developers
Classifier: License :: OSI Approved :: MIT License
Classifier: Operating System :: POSIX
